stylys/__init__.py
Stylys-1.0.1.dist-info/LICENSE
Stylys-1.0.1.dist-info/METADATA
Stylys-1.0.1.dist-info/WHEEL
Stylys-1.0.1.dist-info/top_level.txt
Stylys-1.0.1.dist-info/RECORD
