Metadata-Version: 2.1
Name: Stylys
Version: 1.0.1
Summary: Just a next text styling library for Python.
Home-page: https://github.com/IvulkaCZ/Stylys
Author: Ivulka
Classifier: Development Status :: 3 - Alpha
Classifier: Intended Audience :: Developers
Classifier: License :: OSI Approved :: The Unlicense (Unlicense)
Classifier: Operating System :: Microsoft :: Windows :: Windows 11
Classifier: Programming Language :: Python :: 3.11
Classifier: Programming Language :: Python :: 3 :: Only
Classifier: Topic :: Software Development :: Libraries :: Python Modules
License-File: LICENSE
